
[
    {
     "Key": "King",
     "King": -80,
     "Priest": 80,
     "Merchant": 30,
     "Bartender": 20,
     "Commander": 60,
     "Florist": 30,
     "Saint": 70,
     "Scholar": 80,
     "Alchemist": 60,
     "Monk": 40,
     "Gladiator": 50,
     "Sculptor": 60,
     "Guard": 10,
     "Jester": 50,
     "Adventurer": -30,
     "Sailor": -20,
     "Executioner": -40,
     "Lumberjack": -50,
     "Farmer": -40,
     "Cowboy": -50,
     "Transporter": -10,
     "Warrior": 20,
     "Miner": -50,
     "Beggar": -70,
     "Butcher": -50,
     "Mason": -30,
     "Blacksmith": 30,
     "Bard": 60,
     "Painter": 60,
     "Thief": -80,
     "Slavemaster": 40,
     "Knight": 80,
     "Wizard": 80,
     "Cook": 80,
     "Lancer": 60,
     "Archer": 60,
     "Grandmaster": 80,
     "Noble": 70,
     "Astronomer": 60,
     "Jeweller": 70,
     "Weaver": -40
    },
    {
     "Key": "Priest",
     "King": 80,
     "Priest": 80,
     "Merchant": 40,
     "Bartender": -50,
     "Commander": 20,
     "Florist": 40,
     "Saint": 80,
     "Scholar": 80,
     "Alchemist": 70,
     "Monk": 60,
     "Gladiator": 40,
     "Sculptor": 50,
     "Guard": 50,
     "Jester": 30,
     "Adventurer": 10,
     "Sailor": 10,
     "Executioner": 20,
     "Lumberjack": 20,
     "Farmer": 30,
     "Cowboy": 20,
     "Transporter": 20,
     "Warrior": -50,
     "Miner": 20,
     "Beggar": 20,
     "Butcher": -20,
     "Mason": 30,
     "Blacksmith": 20,
     "Bard": 60,
     "Painter": 30,
     "Thief": -70,
     "Slavemaster": -80,
     "Knight": 50,
     "Wizard": 70,
     "Cook": 30,
     "Lancer": -10,
     "Archer": -10,
     "Grandmaster": 50,
     "Noble": 80,
     "Astronomer": 70,
     "Jeweller": 30,
     "Weaver": 20
    },
    {
     "Key": "Merchant",
     "King": 30,
     "Priest": 40,
     "Merchant": -80,
     "Bartender": 70,
     "Commander": 10,
     "Florist": 40,
     "Saint": -40,
     "Scholar": 80,
     "Alchemist": 30,
     "Monk": -30,
     "Gladiator": -10,
     "Sculptor": 40,
     "Guard": 70,
     "Jester": 30,
     "Adventurer": 60,
     "Sailor": 60,
     "Executioner": 30,
     "Lumberjack": 60,
     "Farmer": 60,
     "Cowboy": 20,
     "Transporter": 60,
     "Warrior": 10,
     "Miner": 50,
     "Beggar": -60,
     "Butcher": 40,
     "Mason": 50,
     "Blacksmith": 70,
     "Bard": -40,
     "Painter": 30,
     "Thief": 40,
     "Slavemaster": 40,
     "Knight": 10,
     "Wizard": 20,
     "Cook": 50,
     "Lancer": -20,
     "Archer": -20,
     "Grandmaster": 30,
     "Noble": 70,
     "Astronomer": 50,
     "Jeweller": 50,
     "Weaver": 60
    },
    {
     "Key": "Bartender",
     "King": 20,
     "Priest": -50,
     "Merchant": 70,
     "Bartender": -50,
     "Commander": 60,
     "Florist": 10,
     "Saint": -50,
     "Scholar": 40,
     "Alchemist": 30,
     "Monk": -80,
     "Gladiator": 60,
     "Sculptor": 30,
     "Guard": 60,
     "Jester": 40,
     "Adventurer": 80,
     "Sailor": 80,
     "Executioner": 50,
     "Lumberjack": 50,
     "Farmer": 50,
     "Cowboy": 50,
     "Transporter": 60,
     "Warrior": 60,
     "Miner": 50,
     "Beggar": -60,
     "Butcher": 50,
     "Mason": 50,
     "Blacksmith": 20,
     "Bard": 70,
     "Painter": 40,
     "Thief": -40,
     "Slavemaster": -30,
     "Knight": 60,
     "Wizard": 40,
     "Cook": 70,
     "Lancer": 50,
     "Archer": 50,
     "Grandmaster": 60,
     "Noble": 80,
     "Astronomer": 50,
     "Jeweller": 40,
     "Weaver": 50
    },
    {
     "Key": "Commander",
     "King": 60,
     "Priest": 20,
     "Merchant": 10,
     "Bartender": 60,
     "Commander": 80,
     "Florist": 40,
     "Saint": 60,
     "Scholar": 50,
     "Alchemist": 50,
     "Monk": -60,
     "Gladiator": 10,
     "Sculptor": -40,
     "Guard": 60,
     "Jester": 20,
     "Adventurer": -50,
     "Sailor": -30,
     "Executioner": -10,
     "Lumberjack": -20,
     "Farmer": -10,
     "Cowboy": -10,
     "Transporter": 10,
     "Warrior": 40,
     "Miner": -20,
     "Beggar": 10,
     "Butcher": 30,
     "Mason": 30,
     "Blacksmith": 70,
     "Bard": 20,
     "Painter": -10,
     "Thief": -80,
     "Slavemaster": -50,
     "Knight": 60,
     "Wizard": 70,
     "Cook": 40,
     "Lancer": 50,
     "Archer": 50,
     "Grandmaster": 80,
     "Noble": 50,
     "Astronomer": 20,
     "Jeweller": 40,
     "Weaver": 20
    },
    {
     "Key": "Florist",
     "King": 30,
     "Priest": 40,
     "Merchant": 40,
     "Bartender": 10,
     "Commander": 40,
     "Florist": 80,
     "Saint": 80,
     "Scholar": 70,
     "Alchemist": 50,
     "Monk": 60,
     "Gladiator": 20,
     "Sculptor": 30,
     "Guard": 30,
     "Jester": 10,
     "Adventurer": 50,
     "Sailor": 50,
     "Executioner": -20,
     "Lumberjack": 30,
     "Farmer": 40,
     "Cowboy": 40,
     "Transporter": 40,
     "Warrior": 50,
     "Miner": 30,
     "Beggar": 50,
     "Butcher": 20,
     "Mason": 30,
     "Blacksmith": 40,
     "Bard": 70,
     "Painter": 60,
     "Thief": -30,
     "Slavemaster": -50,
     "Knight": 60,
     "Wizard": 60,
     "Cook": 40,
     "Lancer": 60,
     "Archer": 50,
     "Grandmaster": 70,
     "Noble": 80,
     "Astronomer": 70,
     "Jeweller": 50,
     "Weaver": 40
    },
    {
     "Key": "Saint",
     "King": 70,
     "Priest": 80,
     "Merchant": -40,
     "Bartender": -50,
     "Commander": 60,
     "Florist": 80,
     "Saint": 80,
     "Scholar": 70,
     "Alchemist": 70,
     "Monk": 80,
     "Gladiator": 40,
     "Sculptor": 60,
     "Guard": 20,
     "Jester": 10,
     "Adventurer": 40,
     "Sailor": 40,
     "Executioner": -80,
     "Lumberjack": 40,
     "Farmer": 30,
     "Cowboy": 30,
     "Transporter": 40,
     "Warrior": 30,
     "Miner": 40,
     "Beggar": 60,
     "Butcher": 40,
     "Mason": 40,
     "Blacksmith": 50,
     "Bard": 60,
     "Painter": 40,
     "Thief": 30,
     "Slavemaster": 10,
     "Knight": 70,
     "Wizard": 60,
     "Cook": 60,
     "Lancer": 60,
     "Archer": 50,
     "Grandmaster": 70,
     "Noble": 30,
     "Astronomer": 80,
     "Jeweller": 20,
     "Weaver": 40
    },
    {
     "Key": "Scholar",
     "King": 80,
     "Priest": 80,
     "Merchant": 80,
     "Bartender": 40,
     "Commander": 50,
     "Florist": 70,
     "Saint": 70,
     "Scholar": 80,
     "Alchemist": 70,
     "Monk": 80,
     "Gladiator": 10,
     "Sculptor": 60,
     "Guard": -20,
     "Jester": 40,
     "Adventurer": 10,
     "Sailor": 30,
     "Executioner": 30,
     "Lumberjack": 40,
     "Farmer": 40,
     "Cowboy": 30,
     "Transporter": 40,
     "Warrior": 10,
     "Miner": 40,
     "Beggar": 40,
     "Butcher": 40,
     "Mason": 50,
     "Blacksmith": 60,
     "Bard": 20,
     "Painter": 60,
     "Thief": -10,
     "Slavemaster": -50,
     "Knight": 20,
     "Wizard": 50,
     "Cook": 50,
     "Lancer": 10,
     "Archer": 10,
     "Grandmaster": 60,
     "Noble": 40,
     "Astronomer": 50,
     "Jeweller": 40,
     "Weaver": 50
    },
    {
     "Key": "Alchemist",
     "King": 60,
     "Priest": 70,
     "Merchant": 30,
     "Bartender": 30,
     "Commander": 50,
     "Florist": 50,
     "Saint": 70,
     "Scholar": 70,
     "Alchemist": 80,
     "Monk": 50,
     "Gladiator": -10,
     "Sculptor": 20,
     "Guard": 10,
     "Jester": -30,
     "Adventurer": 60,
     "Sailor": 50,
     "Executioner": -50,
     "Lumberjack": 60,
     "Farmer": 60,
     "Cowboy": 30,
     "Transporter": 50,
     "Warrior": -30,
     "Miner": 50,
     "Beggar": 20,
     "Butcher": 40,
     "Mason": 10,
     "Blacksmith": -40,
     "Bard": -50,
     "Painter": 20,
     "Thief": -80,
     "Slavemaster": -80,
     "Knight": -20,
     "Wizard": -30,
     "Cook": 60,
     "Lancer": -20,
     "Archer": -30,
     "Grandmaster": -50,
     "Noble": -50,
     "Astronomer": -30,
     "Jeweller": 20,
     "Weaver": 40
    },
    {
     "Key": "Monk",
     "King": 40,
     "Priest": 60,
     "Merchant": -30,
     "Bartender": -80,
     "Commander": -60,
     "Florist": 60,
     "Saint": 80,
     "Scholar": 80,
     "Alchemist": 50,
     "Monk": 80,
     "Gladiator": 50,
     "Sculptor": 50,
     "Guard": 30,
     "Jester": 30,
     "Adventurer": 50,
     "Sailor": 50,
     "Executioner": -80,
     "Lumberjack": 50,
     "Farmer": 50,
     "Cowboy": 50,
     "Transporter": 50,
     "Warrior": -30,
     "Miner": 50,
     "Beggar": 80,
     "Butcher": 50,
     "Mason": 50,
     "Blacksmith": 50,
     "Bard": 80,
     "Painter": 50,
     "Thief": 40,
     "Slavemaster": -30,
     "Knight": -10,
     "Wizard": -10,
     "Cook": 50,
     "Lancer": -10,
     "Archer": -10,
     "Grandmaster": -20,
     "Noble": -60,
     "Astronomer": 40,
     "Jeweller": 40,
     "Weaver": 50
    },
    {
     "Key": "Gladiator",
     "King": 50,
     "Priest": 40,
     "Merchant": -10,
     "Bartender": 60,
     "Commander": 10,
     "Florist": 20,
     "Saint": 40,
     "Scholar": 10,
     "Alchemist": -10,
     "Monk": 50,
     "Gladiator": 80,
     "Sculptor": 60,
     "Guard": 70,
     "Jester": 20,
     "Adventurer": 50,
     "Sailor": 50,
     "Executioner": 60,
     "Lumberjack": 50,
     "Farmer": 40,
     "Cowboy": 30,
     "Transporter": 40,
     "Warrior": 60,
     "Miner": 60,
     "Beggar": 10,
     "Butcher": 30,
     "Mason": 10,
     "Blacksmith": 60,
     "Bard": 20,
     "Painter": -10,
     "Thief": 40,
     "Slavemaster": 60,
     "Knight": 10,
     "Wizard": 20,
     "Cook": 40,
     "Lancer": 10,
     "Archer": 10,
     "Grandmaster": 40,
     "Noble": -50,
     "Astronomer": -30,
     "Jeweller": -50,
     "Weaver": 20
    },
    {
     "Key": "Sculptor",
     "King": 60,
     "Priest": 50,
     "Merchant": 40,
     "Bartender": 30,
     "Commander": -40,
     "Florist": 30,
     "Saint": 60,
     "Scholar": 60,
     "Alchemist": 20,
     "Monk": 80,
     "Gladiator": 60,
     "Sculptor": 50,
     "Guard": 10,
     "Jester": 30,
     "Adventurer": 40,
     "Sailor": 40,
     "Executioner": -50,
     "Lumberjack": 30,
     "Farmer": 20,
     "Cowboy": 10,
     "Transporter": 20,
     "Warrior": 40,
     "Miner": 20,
     "Beggar": 40,
     "Butcher": 20,
     "Mason": 80,
     "Blacksmith": 40,
     "Bard": 20,
     "Painter": 70,
     "Thief": -60,
     "Slavemaster": -70,
     "Knight": 60,
     "Wizard": 60,
     "Cook": 50,
     "Lancer": 60,
     "Archer": 60,
     "Grandmaster": 80,
     "Noble": 70,
     "Astronomer": 70,
     "Jeweller": 60,
     "Weaver": 40
    },
    {
     "Key": "Guard",
     "King": 10,
     "Priest": 50,
     "Merchant": 70,
     "Bartender": 60,
     "Commander": 60,
     "Florist": 30,
     "Saint": 20,
     "Scholar": -20,
     "Alchemist": 10,
     "Monk": 30,
     "Gladiator": 70,
     "Sculptor": 10,
     "Guard": 80,
     "Jester": 60,
     "Adventurer": 60,
     "Sailor": 60,
     "Executioner": 40,
     "Lumberjack": 40,
     "Farmer": 30,
     "Cowboy": 30,
     "Transporter": 40,
     "Warrior": 50,
     "Miner": 30,
     "Beggar": 10,
     "Butcher": 20,
     "Mason": 30,
     "Blacksmith": 60,
     "Bard": 30,
     "Painter": 20,
     "Thief": -80,
     "Slavemaster": -50,
     "Knight": 80,
     "Wizard": 70,
     "Cook": 50,
     "Lancer": 60,
     "Archer": 60,
     "Grandmaster": 80,
     "Noble": 80,
     "Astronomer": 70,
     "Jeweller": 40,
     "Weaver": 40
    },
    {
     "Key": "Jester",
     "King": 50,
     "Priest": 30,
     "Merchant": 30,
     "Bartender": 40,
     "Commander": 20,
     "Florist": 10,
     "Saint": 10,
     "Scholar": 40,
     "Alchemist": -30,
     "Monk": 30,
     "Gladiator": 20,
     "Sculptor": 30,
     "Guard": 60,
     "Jester": 80,
     "Adventurer": 70,
     "Sailor": 60,
     "Executioner": -50,
     "Lumberjack": 50,
     "Farmer": 40,
     "Cowboy": 40,
     "Transporter": 40,
     "Warrior": 50,
     "Miner": 40,
     "Beggar": 20,
     "Butcher": 40,
     "Mason": 40,
     "Blacksmith": 50,
     "Bard": 60,
     "Painter": 40,
     "Thief": -30,
     "Slavemaster": -20,
     "Knight": 40,
     "Wizard": 50,
     "Cook": 60,
     "Lancer": 40,
     "Archer": 40,
     "Grandmaster": 50,
     "Noble": 70,
     "Astronomer": 50,
     "Jeweller": 60,
     "Weaver": 20
    },
    {
     "Key": "Adventurer",
     "King": -30,
     "Priest": 10,
     "Merchant": 60,
     "Bartender": 80,
     "Commander": -50,
     "Florist": 50,
     "Saint": 40,
     "Scholar": 10,
     "Alchemist": 60,
     "Monk": 50,
     "Gladiator": 50,
     "Sculptor": 40,
     "Guard": 60,
     "Jester": 70,
     "Adventurer": 80,
     "Sailor": 80,
     "Executioner": -20,
     "Lumberjack": 70,
     "Farmer": 70,
     "Cowboy": 70,
     "Transporter": 70,
     "Warrior": 60,
     "Miner": 70,
     "Beggar": 60,
     "Butcher": 70,
     "Mason": 80,
     "Blacksmith": 80,
     "Bard": 80,
     "Painter": 50,
     "Thief": 60,
     "Slavemaster": 60,
     "Knight": 50,
     "Wizard": 50,
     "Cook": 60,
     "Lancer": 50,
     "Archer": 50,
     "Grandmaster": 70,
     "Noble": 40,
     "Astronomer": 60,
     "Jeweller": 50,
     "Weaver": 60
    },
    {
     "Key": "Sailor",
     "King": -20,
     "Priest": 10,
     "Merchant": 60,
     "Bartender": 80,
     "Commander": -30,
     "Florist": 50,
     "Saint": 40,
     "Scholar": 30,
     "Alchemist": 50,
     "Monk": 50,
     "Gladiator": 50,
     "Sculptor": 40,
     "Guard": 60,
     "Jester": 60,
     "Adventurer": 80,
     "Sailor": 80,
     "Executioner": -20,
     "Lumberjack": 50,
     "Farmer": 40,
     "Cowboy": 40,
     "Transporter": 50,
     "Warrior": 30,
     "Miner": 40,
     "Beggar": 50,
     "Butcher": 40,
     "Mason": 50,
     "Blacksmith": 70,
     "Bard": 30,
     "Painter": 20,
     "Thief": -70,
     "Slavemaster": 30,
     "Knight": 10,
     "Wizard": 20,
     "Cook": 70,
     "Lancer": 10,
     "Archer": 20,
     "Grandmaster": -10,
     "Noble": 30,
     "Astronomer": 50,
     "Jeweller": 10,
     "Weaver": 50
    },
    {
     "Key": "Executioner",
     "King": -40,
     "Priest": 20,
     "Merchant": 30,
     "Bartender": 50,
     "Commander": -10,
     "Florist": -20,
     "Saint": -80,
     "Scholar": 30,
     "Alchemist": -50,
     "Monk": -80,
     "Gladiator": 60,
     "Sculptor": -50,
     "Guard": 40,
     "Jester": -50,
     "Adventurer": -20,
     "Sailor": -20,
     "Executioner": 70,
     "Lumberjack": -60,
     "Farmer": -50,
     "Cowboy": -60,
     "Transporter": -60,
     "Warrior": 20,
     "Miner": -60,
     "Beggar": -80,
     "Butcher": 30,
     "Mason": -60,
     "Blacksmith": -50,
     "Bard": 10,
     "Painter": -30,
     "Thief": -80,
     "Slavemaster": -60,
     "Knight": 60,
     "Wizard": 30,
     "Cook": -60,
     "Lancer": 50,
     "Archer": 30,
     "Grandmaster": 70,
     "Noble": -70,
     "Astronomer": 30,
     "Jeweller": -60,
     "Weaver": -60
    },
    {
     "Key": "Lumberjack",
     "King": -50,
     "Priest": 20,
     "Merchant": 60,
     "Bartender": 50,
     "Commander": -20,
     "Florist": 30,
     "Saint": 40,
     "Scholar": 40,
     "Alchemist": 60,
     "Monk": 50,
     "Gladiator": 50,
     "Sculptor": 30,
     "Guard": 40,
     "Jester": 50,
     "Adventurer": 70,
     "Sailor": 50,
     "Executioner": -60,
     "Lumberjack": 80,
     "Farmer": 50,
     "Cowboy": 70,
     "Transporter": 60,
     "Warrior": 30,
     "Miner": 60,
     "Beggar": 40,
     "Butcher": 60,
     "Mason": 70,
     "Blacksmith": 80,
     "Bard": -50,
     "Painter": -20,
     "Thief": 10,
     "Slavemaster": 10,
     "Knight": -40,
     "Wizard": -60,
     "Cook": 70,
     "Lancer": -30,
     "Archer": -70,
     "Grandmaster": -10,
     "Noble": -60,
     "Astronomer": 40,
     "Jeweller": 10,
     "Weaver": 70
    },
    {
     "Key": "Farmer",
     "King": -40,
     "Priest": 30,
     "Merchant": 60,
     "Bartender": 50,
     "Commander": -10,
     "Florist": 40,
     "Saint": 30,
     "Scholar": 40,
     "Alchemist": 60,
     "Monk": 50,
     "Gladiator": 40,
     "Sculptor": 20,
     "Guard": 30,
     "Jester": 40,
     "Adventurer": 70,
     "Sailor": 40,
     "Executioner": -50,
     "Lumberjack": 50,
     "Farmer": 80,
     "Cowboy": 80,
     "Transporter": 60,
     "Warrior": 20,
     "Miner": 70,
     "Beggar": 50,
     "Butcher": 30,
     "Mason": 80,
     "Blacksmith": 60,
     "Bard": 10,
     "Painter": -40,
     "Thief": -80,
     "Slavemaster": 20,
     "Knight": 10,
     "Wizard": 10,
     "Cook": 60,
     "Lancer": 10,
     "Archer": 10,
     "Grandmaster": 30,
     "Noble": -60,
     "Astronomer": 20,
     "Jeweller": -10,
     "Weaver": 60
    },
    {
     "Key": "Cowboy",
     "King": -50,
     "Priest": 20,
     "Merchant": 20,
     "Bartender": 50,
     "Commander": -10,
     "Florist": 40,
     "Saint": 30,
     "Scholar": 30,
     "Alchemist": 30,
     "Monk": 50,
     "Gladiator": 30,
     "Sculptor": 10,
     "Guard": 30,
     "Jester": 40,
     "Adventurer": 70,
     "Sailor": 40,
     "Executioner": -60,
     "Lumberjack": 70,
     "Farmer": 80,
     "Cowboy": 80,
     "Transporter": 50,
     "Warrior": 60,
     "Miner": 40,
     "Beggar": 60,
     "Butcher": -80,
     "Mason": 70,
     "Blacksmith": 40,
     "Bard": 10,
     "Painter": -20,
     "Thief": 20,
     "Slavemaster": 10,
     "Knight": -10,
     "Wizard": -30,
     "Cook": 60,
     "Lancer": -20,
     "Archer": -40,
     "Grandmaster": -40,
     "Noble": -70,
     "Astronomer": 50,
     "Jeweller": 10,
     "Weaver": 70
    },
    {
     "Key": "Transporter",
     "King": -10,
     "Priest": 20,
     "Merchant": 60,
     "Bartender": 60,
     "Commander": 10,
     "Florist": 40,
     "Saint": 40,
     "Scholar": 40,
     "Alchemist": 50,
     "Monk": 50,
     "Gladiator": 40,
     "Sculptor": 20,
     "Guard": 40,
     "Jester": 40,
     "Adventurer": 70,
     "Sailor": 50,
     "Executioner": -60,
     "Lumberjack": 60,
     "Farmer": 60,
     "Cowboy": 50,
     "Transporter": -50,
     "Warrior": 40,
     "Miner": 50,
     "Beggar": 10,
     "Butcher": 40,
     "Mason": 50,
     "Blacksmith": 70,
     "Bard": 20,
     "Painter": 10,
     "Thief": -60,
     "Slavemaster": 60,
     "Knight": 20,
     "Wizard": 30,
     "Cook": 70,
     "Lancer": 10,
     "Archer": 30,
     "Grandmaster": 20,
     "Noble": 80,
     "Astronomer": 20,
     "Jeweller": 80,
     "Weaver": 40
    },
    {
     "Key": "Warrior",
     "King": 20,
     "Priest": -50,
     "Merchant": 10,
     "Bartender": 60,
     "Commander": 40,
     "Florist": 50,
     "Saint": 30,
     "Scholar": 10,
     "Alchemist": -30,
     "Monk": -30,
     "Gladiator": 60,
     "Sculptor": 40,
     "Guard": 50,
     "Jester": 50,
     "Adventurer": 60,
     "Sailor": 30,
     "Executioner": 20,
     "Lumberjack": 30,
     "Farmer": 20,
     "Cowboy": 60,
     "Transporter": 40,
     "Warrior": 80,
     "Miner": 50,
     "Beggar": 40,
     "Butcher": 70,
     "Mason": 50,
     "Blacksmith": 80,
     "Bard": 60,
     "Painter": 10,
     "Thief": -30,
     "Slavemaster": -40,
     "Knight": 60,
     "Wizard": 70,
     "Cook": 20,
     "Lancer": 50,
     "Archer": 50,
     "Grandmaster": 60,
     "Noble": 40,
     "Astronomer": 10,
     "Jeweller": -20,
     "Weaver": 10
    },
    {
     "Key": "Miner",
     "King": -50,
     "Priest": 20,
     "Merchant": 50,
     "Bartender": 50,
     "Commander": -20,
     "Florist": 30,
     "Saint": 40,
     "Scholar": 40,
     "Alchemist": 50,
     "Monk": 50,
     "Gladiator": 60,
     "Sculptor": 20,
     "Guard": 30,
     "Jester": 40,
     "Adventurer": 70,
     "Sailor": 40,
     "Executioner": -60,
     "Lumberjack": 60,
     "Farmer": 70,
     "Cowboy": 40,
     "Transporter": 50,
     "Warrior": 50,
     "Miner": 80,
     "Beggar": 50,
     "Butcher": 40,
     "Mason": 70,
     "Blacksmith": 80,
     "Bard": 10,
     "Painter": -40,
     "Thief": 40,
     "Slavemaster": -20,
     "Knight": -20,
     "Wizard": -40,
     "Cook": 50,
     "Lancer": -20,
     "Archer": -20,
     "Grandmaster": -10,
     "Noble": -60,
     "Astronomer": -20,
     "Jeweller": -40,
     "Weaver": 50
    },
    {
     "Key": "Beggar",
     "King": -70,
     "Priest": 20,
     "Merchant": -60,
     "Bartender": -60,
     "Commander": 10,
     "Florist": 50,
     "Saint": 60,
     "Scholar": 40,
     "Alchemist": 20,
     "Monk": 80,
     "Gladiator": 10,
     "Sculptor": 40,
     "Guard": 10,
     "Jester": 20,
     "Adventurer": 60,
     "Sailor": 50,
     "Executioner": -80,
     "Lumberjack": 40,
     "Farmer": 50,
     "Cowboy": 60,
     "Transporter": 10,
     "Warrior": 40,
     "Miner": 50,
     "Beggar": 80,
     "Butcher": 70,
     "Mason": 50,
     "Blacksmith": 10,
     "Bard": 50,
     "Painter": 10,
     "Thief": 60,
     "Slavemaster": 20,
     "Knight": -50,
     "Wizard": -10,
     "Cook": 80,
     "Lancer": -10,
     "Archer": -20,
     "Grandmaster": 20,
     "Noble": 30,
     "Astronomer": 10,
     "Jeweller": -60,
     "Weaver": 10
    },
    {
     "Key": "Butcher",
     "King": -50,
     "Priest": -20,
     "Merchant": 40,
     "Bartender": 50,
     "Commander": 30,
     "Florist": 20,
     "Saint": 40,
     "Scholar": 40,
     "Alchemist": 40,
     "Monk": 50,
     "Gladiator": 30,
     "Sculptor": 20,
     "Guard": 20,
     "Jester": 40,
     "Adventurer": 70,
     "Sailor": 40,
     "Executioner": 30,
     "Lumberjack": 60,
     "Farmer": 30,
     "Cowboy": -80,
     "Transporter": 40,
     "Warrior": 70,
     "Miner": 40,
     "Beggar": 70,
     "Butcher": 50,
     "Mason": 80,
     "Blacksmith": 80,
     "Bard": 40,
     "Painter": -40,
     "Thief": 10,
     "Slavemaster": 40,
     "Knight": -40,
     "Wizard": -10,
     "Cook": 80,
     "Lancer": -10,
     "Archer": -20,
     "Grandmaster": 10,
     "Noble": -60,
     "Astronomer": -20,
     "Jeweller": 50,
     "Weaver": 10
    },
    {
     "Key": "Mason",
     "King": -30,
     "Priest": 30,
     "Merchant": 50,
     "Bartender": 50,
     "Commander": 30,
     "Florist": 30,
     "Saint": 40,
     "Scholar": 50,
     "Alchemist": 10,
     "Monk": 50,
     "Gladiator": 10,
     "Sculptor": 80,
     "Guard": 30,
     "Jester": 40,
     "Adventurer": 80,
     "Sailor": 50,
     "Executioner": -60,
     "Lumberjack": 70,
     "Farmer": 80,
     "Cowboy": 70,
     "Transporter": 50,
     "Warrior": 50,
     "Miner": 70,
     "Beggar": 50,
     "Butcher": 80,
     "Mason": 60,
     "Blacksmith": 70,
     "Bard": 10,
     "Painter": 20,
     "Thief": -20,
     "Slavemaster": -60,
     "Knight": 10,
     "Wizard": 10,
     "Cook": 40,
     "Lancer": 10,
     "Archer": 20,
     "Grandmaster": 40,
     "Noble": 80,
     "Astronomer": 10,
     "Jeweller": 50,
     "Weaver": 20
    },
    {
     "Key": "Blacksmith",
     "King": 30,
     "Priest": 20,
     "Merchant": 70,
     "Bartender": 20,
     "Commander": 70,
     "Florist": 40,
     "Saint": 50,
     "Scholar": 60,
     "Alchemist": -40,
     "Monk": 50,
     "Gladiator": 60,
     "Sculptor": 40,
     "Guard": 60,
     "Jester": 50,
     "Adventurer": 80,
     "Sailor": 70,
     "Executioner": -50,
     "Lumberjack": 80,
     "Farmer": 60,
     "Cowboy": 40,
     "Transporter": 70,
     "Warrior": 80,
     "Miner": 80,
     "Beggar": 10,
     "Butcher": 80,
     "Mason": 70,
     "Blacksmith": 80,
     "Bard": 40,
     "Painter": 10,
     "Thief": -70,
     "Slavemaster": -50,
     "Knight": 40,
     "Wizard": 50,
     "Cook": -20,
     "Lancer": 40,
     "Archer": 50,
     "Grandmaster": 60,
     "Noble": -30,
     "Astronomer": -70,
     "Jeweller": 60,
     "Weaver": 10
    },
    {
     "Key": "Bard",
     "King": 60,
     "Priest": 60,
     "Merchant": -40,
     "Bartender": 70,
     "Commander": 20,
     "Florist": 70,
     "Saint": 60,
     "Scholar": 20,
     "Alchemist": -50,
     "Monk": 80,
     "Gladiator": 20,
     "Sculptor": 20,
     "Guard": 30,
     "Jester": 60,
     "Adventurer": 80,
     "Sailor": 30,
     "Executioner": 10,
     "Lumberjack": -50,
     "Farmer": 10,
     "Cowboy": 10,
     "Transporter": 20,
     "Warrior": 60,
     "Miner": 10,
     "Beggar": 50,
     "Butcher": 40,
     "Mason": 10,
     "Blacksmith": 40,
     "Bard": 80,
     "Painter": 50,
     "Thief": 70,
     "Slavemaster": 40,
     "Knight": 70,
     "Wizard": 60,
     "Cook": -20,
     "Lancer": 50,
     "Archer": 50,
     "Grandmaster": 80,
     "Noble": 80,
     "Astronomer": 30,
     "Jeweller": 10,
     "Weaver": -20
    },
    {
     "Key": "Painter",
     "King": 60,
     "Priest": 30,
     "Merchant": 30,
     "Bartender": 40,
     "Commander": -10,
     "Florist": 60,
     "Saint": 40,
     "Scholar": 60,
     "Alchemist": 20,
     "Monk": 50,
     "Gladiator": -10,
     "Sculptor": 70,
     "Guard": 20,
     "Jester": 40,
     "Adventurer": 50,
     "Sailor": 20,
     "Executioner": -30,
     "Lumberjack": -20,
     "Farmer": -40,
     "Cowboy": -20,
     "Transporter": 10,
     "Warrior": 10,
     "Miner": -40,
     "Beggar": 10,
     "Butcher": -40,
     "Mason": 20,
     "Blacksmith": 10,
     "Bard": 50,
     "Painter": 60,
     "Thief": 20,
     "Slavemaster": 10,
     "Knight": 60,
     "Wizard": 60,
     "Cook": -30,
     "Lancer": 60,
     "Archer": 60,
     "Grandmaster": 70,
     "Noble": 80,
     "Astronomer": 20,
     "Jeweller": 40,
     "Weaver": 10
    },
    {
     "Key": "Thief",
     "King": -80,
     "Priest": -70,
     "Merchant": 40,
     "Bartender": -40,
     "Commander": -80,
     "Florist": -30,
     "Saint": 30,
     "Scholar": -10,
     "Alchemist": -80,
     "Monk": 40,
     "Gladiator": 40,
     "Sculptor": -60,
     "Guard": -80,
     "Jester": -30,
     "Adventurer": 60,
     "Sailor": -70,
     "Executioner": -80,
     "Lumberjack": 10,
     "Farmer": -80,
     "Cowboy": 20,
     "Transporter": -60,
     "Warrior": -30,
     "Miner": 40,
     "Beggar": 60,
     "Butcher": 10,
     "Mason": -20,
     "Blacksmith": -70,
     "Bard": 70,
     "Painter": 20,
     "Thief": 80,
     "Slavemaster": 80,
     "Knight": -30,
     "Wizard": -10,
     "Cook": -40,
     "Lancer": -50,
     "Archer": -60,
     "Grandmaster": -50,
     "Noble": -80,
     "Astronomer": 20,
     "Jeweller": 10,
     "Weaver": 30
    },
    {
     "Key": "Slavemaster",
     "King": 40,
     "Priest": -80,
     "Merchant": 40,
     "Bartender": -30,
     "Commander": -50,
     "Florist": -50,
     "Saint": 10,
     "Scholar": -50,
     "Alchemist": -80,
     "Monk": -30,
     "Gladiator": 60,
     "Sculptor": -70,
     "Guard": -50,
     "Jester": -20,
     "Adventurer": 60,
     "Sailor": 30,
     "Executioner": -60,
     "Lumberjack": 10,
     "Farmer": 20,
     "Cowboy": 10,
     "Transporter": 60,
     "Warrior": -40,
     "Miner": -20,
     "Beggar": 20,
     "Butcher": 40,
     "Mason": -60,
     "Blacksmith": -50,
     "Bard": 40,
     "Painter": 10,
     "Thief": 80,
     "Slavemaster": 80,
     "Knight": 30,
     "Wizard": 10,
     "Cook": -80,
     "Lancer": 40,
     "Archer": 50,
     "Grandmaster": 20,
     "Noble": 80,
     "Astronomer": 20,
     "Jeweller": 10,
     "Weaver": 10
    },
    {
     "Key": "Knight",
     "King": 80,
     "Priest": 50,
     "Merchant": 10,
     "Bartender": 60,
     "Commander": 60,
     "Florist": 60,
     "Saint": 70,
     "Scholar": 20,
     "Alchemist": -20,
     "Monk": -10,
     "Gladiator": 10,
     "Sculptor": 60,
     "Guard": 80,
     "Jester": 40,
     "Adventurer": 50,
     "Sailor": 10,
     "Executioner": 60,
     "Lumberjack": -40,
     "Farmer": 10,
     "Cowboy": -10,
     "Transporter": 20,
     "Warrior": 60,
     "Miner": -20,
     "Beggar": -50,
     "Butcher": -40,
     "Mason": 10,
     "Blacksmith": 40,
     "Bard": 70,
     "Painter": 60,
     "Thief": -30,
     "Slavemaster": 30,
     "Knight": 80,
     "Wizard": 70,
     "Cook": 60,
     "Lancer": 80,
     "Archer": 80,
     "Grandmaster": 60,
     "Noble": 50,
     "Astronomer": 70,
     "Jeweller": 10,
     "Weaver": 30
    },
    {
     "Key": "Wizard",
     "King": 80,
     "Priest": 70,
     "Merchant": 20,
     "Bartender": 40,
     "Commander": 70,
     "Florist": 60,
     "Saint": 60,
     "Scholar": 50,
     "Alchemist": -30,
     "Monk": -10,
     "Gladiator": 20,
     "Sculptor": 60,
     "Guard": 70,
     "Jester": 50,
     "Adventurer": 50,
     "Sailor": 20,
     "Executioner": 30,
     "Lumberjack": -60,
     "Farmer": 10,
     "Cowboy": -30,
     "Transporter": 30,
     "Warrior": 70,
     "Miner": -40,
     "Beggar": -10,
     "Butcher": -10,
     "Mason": 10,
     "Blacksmith": 50,
     "Bard": 60,
     "Painter": 60,
     "Thief": -10,
     "Slavemaster": 10,
     "Knight": 70,
     "Wizard": 80,
     "Cook": 50,
     "Lancer": 20,
     "Archer": 30,
     "Grandmaster": 60,
     "Noble": 70,
     "Astronomer": 10,
     "Jeweller": 20,
     "Weaver": -10
    },
    {
     "Key": "Cook",
     "King": 80,
     "Priest": 30,
     "Merchant": 50,
     "Bartender": 70,
     "Commander": 40,
     "Florist": 40,
     "Saint": 60,
     "Scholar": 50,
     "Alchemist": 60,
     "Monk": 50,
     "Gladiator": 40,
     "Sculptor": 50,
     "Guard": 50,
     "Jester": 60,
     "Adventurer": 60,
     "Sailor": 70,
     "Executioner": -60,
     "Lumberjack": 70,
     "Farmer": 60,
     "Cowboy": 60,
     "Transporter": 70,
     "Warrior": 20,
     "Miner": 50,
     "Beggar": 80,
     "Butcher": 80,
     "Mason": 40,
     "Blacksmith": -20,
     "Bard": -20,
     "Painter": -30,
     "Thief": -40,
     "Slavemaster": -80,
     "Knight": 60,
     "Wizard": 50,
     "Cook": -80,
     "Lancer": 10,
     "Archer": 20,
     "Grandmaster": 60,
     "Noble": 70,
     "Astronomer": 10,
     "Jeweller": 50,
     "Weaver": 70
    },
    {
     "Key": "Lancer",
     "King": 60,
     "Priest": -10,
     "Merchant": -20,
     "Bartender": 50,
     "Commander": 50,
     "Florist": 60,
     "Saint": 60,
     "Scholar": 10,
     "Alchemist": -20,
     "Monk": -10,
     "Gladiator": 10,
     "Sculptor": 60,
     "Guard": 60,
     "Jester": 40,
     "Adventurer": 50,
     "Sailor": 10,
     "Executioner": 50,
     "Lumberjack": -30,
     "Farmer": 10,
     "Cowboy": -20,
     "Transporter": 10,
     "Warrior": 50,
     "Miner": -20,
     "Beggar": -10,
     "Butcher": -10,
     "Mason": 10,
     "Blacksmith": 40,
     "Bard": 50,
     "Painter": 60,
     "Thief": -50,
     "Slavemaster": 40,
     "Knight": 80,
     "Wizard": 20,
     "Cook": 10,
     "Lancer": 60,
     "Archer": 40,
     "Grandmaster": 80,
     "Noble": 60,
     "Astronomer": 70,
     "Jeweller": 40,
     "Weaver": 10
    },
    {
     "Key": "Archer",
     "King": 60,
     "Priest": -10,
     "Merchant": -20,
     "Bartender": 50,
     "Commander": 50,
     "Florist": 50,
     "Saint": 50,
     "Scholar": 10,
     "Alchemist": -30,
     "Monk": -10,
     "Gladiator": 10,
     "Sculptor": 60,
     "Guard": 60,
     "Jester": 40,
     "Adventurer": 50,
     "Sailor": 20,
     "Executioner": 30,
     "Lumberjack": -70,
     "Farmer": 10,
     "Cowboy": -40,
     "Transporter": 30,
     "Warrior": 50,
     "Miner": -20,
     "Beggar": -20,
     "Butcher": -20,
     "Mason": 20,
     "Blacksmith": 50,
     "Bard": 50,
     "Painter": 60,
     "Thief": -60,
     "Slavemaster": 50,
     "Knight": 80,
     "Wizard": 30,
     "Cook": 20,
     "Lancer": 40,
     "Archer": -20,
     "Grandmaster": 50,
     "Noble": 20,
     "Astronomer": 50,
     "Jeweller": 10,
     "Weaver": 80
    },
    {
     "Key": "Grandmaster",
     "King": 80,
     "Priest": 50,
     "Merchant": 30,
     "Bartender": 60,
     "Commander": 80,
     "Florist": 70,
     "Saint": 70,
     "Scholar": 60,
     "Alchemist": -50,
     "Monk": -20,
     "Gladiator": 40,
     "Sculptor": 80,
     "Guard": 80,
     "Jester": 50,
     "Adventurer": 70,
     "Sailor": -10,
     "Executioner": 70,
     "Lumberjack": -10,
     "Farmer": 30,
     "Cowboy": -40,
     "Transporter": 20,
     "Warrior": 60,
     "Miner": -10,
     "Beggar": 20,
     "Butcher": 10,
     "Mason": 40,
     "Blacksmith": 60,
     "Bard": 80,
     "Painter": 70,
     "Thief": -50,
     "Slavemaster": 20,
     "Knight": 60,
     "Wizard": 60,
     "Cook": 60,
     "Lancer": 80,
     "Archer": 50,
     "Grandmaster": 80,
     "Noble": 80,
     "Astronomer": 80,
     "Jeweller": 40,
     "Weaver": 20
    },
    {
     "Key": "Noble",
     "King": 70,
     "Priest": 80,
     "Merchant": 70,
     "Bartender": 80,
     "Commander": 50,
     "Florist": 80,
     "Saint": 30,
     "Scholar": 40,
     "Alchemist": -50,
     "Monk": -60,
     "Gladiator": -50,
     "Sculptor": 70,
     "Guard": 80,
     "Jester": 70,
     "Adventurer": 40,
     "Sailor": 30,
     "Executioner": -70,
     "Lumberjack": -60,
     "Farmer": -60,
     "Cowboy": -70,
     "Transporter": 80,
     "Warrior": 40,
     "Miner": -60,
     "Beggar": 30,
     "Butcher": -60,
     "Mason": 80,
     "Blacksmith": -30,
     "Bard": 80,
     "Painter": 80,
     "Thief": -80,
     "Slavemaster": 80,
     "Knight": 50,
     "Wizard": 70,
     "Cook": 70,
     "Lancer": 60,
     "Archer": 20,
     "Grandmaster": 80,
     "Noble": -60,
     "Astronomer": 30,
     "Jeweller": 80,
     "Weaver": 40
    },
    {
     "Key": "Astronomer",
     "King": 60,
     "Priest": 70,
     "Merchant": 50,
     "Bartender": 50,
     "Commander": 20,
     "Florist": 70,
     "Saint": 80,
     "Scholar": 50,
     "Alchemist": -30,
     "Monk": 40,
     "Gladiator": -30,
     "Sculptor": 70,
     "Guard": 70,
     "Jester": 50,
     "Adventurer": 60,
     "Sailor": 50,
     "Executioner": 30,
     "Lumberjack": 40,
     "Farmer": 20,
     "Cowboy": 50,
     "Transporter": 20,
     "Warrior": 10,
     "Miner": -20,
     "Beggar": 10,
     "Butcher": -20,
     "Mason": 10,
     "Blacksmith": -70,
     "Bard": 30,
     "Painter": 20,
     "Thief": 20,
     "Slavemaster": 20,
     "Knight": 70,
     "Wizard": 10,
     "Cook": 10,
     "Lancer": 70,
     "Archer": 50,
     "Grandmaster": 80,
     "Noble": 30,
     "Astronomer": -60,
     "Jeweller": 70,
     "Weaver": 20
    },
    {
     "Key": "Jeweller",
     "King": 70,
     "Priest": 30,
     "Merchant": 50,
     "Bartender": 40,
     "Commander": 40,
     "Florist": 50,
     "Saint": 20,
     "Scholar": 40,
     "Alchemist": 20,
     "Monk": 40,
     "Gladiator": -50,
     "Sculptor": 60,
     "Guard": 40,
     "Jester": 60,
     "Adventurer": 50,
     "Sailor": 10,
     "Executioner": -60,
     "Lumberjack": 10,
     "Farmer": -10,
     "Cowboy": 10,
     "Transporter": 80,
     "Warrior": -20,
     "Miner": -40,
     "Beggar": -60,
     "Butcher": 50,
     "Mason": 50,
     "Blacksmith": 60,
     "Bard": 10,
     "Painter": 40,
     "Thief": 10,
     "Slavemaster": 10,
     "Knight": 10,
     "Wizard": 20,
     "Cook": 50,
     "Lancer": 40,
     "Archer": 10,
     "Grandmaster": 40,
     "Noble": 80,
     "Astronomer": 70,
     "Jeweller": 80,
     "Weaver": 40
    },
    {
     "Key": "Weaver",
     "King": -40,
     "Priest": 20,
     "Merchant": 60,
     "Bartender": 50,
     "Commander": 20,
     "Florist": 40,
     "Saint": 40,
     "Scholar": 50,
     "Alchemist": 40,
     "Monk": 50,
     "Gladiator": 20,
     "Sculptor": 40,
     "Guard": 40,
     "Jester": 20,
     "Adventurer": 60,
     "Sailor": 50,
     "Executioner": -60,
     "Lumberjack": 70,
     "Farmer": 60,
     "Cowboy": 70,
     "Transporter": 40,
     "Warrior": 10,
     "Miner": 50,
     "Beggar": 10,
     "Butcher": 10,
     "Mason": 20,
     "Blacksmith": 10,
     "Bard": -20,
     "Painter": 10,
     "Thief": 30,
     "Slavemaster": 10,
     "Knight": 30,
     "Wizard": -10,
     "Cook": 70,
     "Lancer": 10,
     "Archer": 80,
     "Grandmaster": 20,
     "Noble": 40,
     "Astronomer": 20,
     "Jeweller": 40,
     "Weaver": 80
    }
   ]